CONTRIBUTING.rst
HISTORY.rst
LICENSE
MANIFEST.in
README.rst
setup.cfg
setup.py
snowline.py
docs/Makefile
docs/conf.py
docs/contributing.rst
docs/history.rst
docs/index.rst
docs/installation.rst
docs/issues.rst
docs/make.bat
docs/modules.rst
docs/readme.rst
docs/snowline.rst
snowline.egg-info/PKG-INFO
snowline.egg-info/SOURCES.txt
snowline.egg-info/dependency_links.txt
snowline.egg-info/requires.txt
snowline.egg-info/top_level.txt
tests/test_run.py