Metadata-Version: 2.1
Name: snowline
Version: 0.6.3
Summary: Fit and compare complex models quickly. Laplace Approximation, Variational Bayes, Importance Sampling.
Home-page: https://github.com/JohannesBuchner/snowline
Author: Johannes Buchner
Author-email: johannes.buchner.acad@gmx.com
License: GNU General Public License v3
Keywords: snowline
Classifier: Development Status :: 2 - Pre-Alpha
Classifier: Intended Audience :: Developers
Classifier: License :: OSI Approved :: GNU General Public License v3 (GPLv3)
Classifier: Natural Language :: English
Classifier: Programming Language :: Python :: 2
Classifier: Programming Language :: Python :: 2.7
Classifier: Programming Language :: Python :: 3
Classifier: Programming Language :: Python :: 3.5
Classifier: Programming Language :: Python :: 3.6
Classifier: Programming Language :: Python :: 3.7
Requires-Python: >=2.7, !=3.0.*, !=3.1.*, !=3.2.*, !=3.3.*, !=3.4.*
Provides-Extra: plot
License-File: LICENSE
